aider/__init__.py
aider/__main__.py
aider/args.py
aider/args_formatter.py
aider/commands.py
aider/diffs.py
aider/dump.py
aider/gui.py
aider/help.py
aider/help_pats.py
aider/history.py
aider/io.py
aider/linter.py
aider/llm.py
aider/main.py
aider/mdstream.py
aider/models.py
aider/prompts.py
aider/repo.py
aider/repomap.py
aider/scrape.py
aider/sendchat.py
aider/urls.py
aider/utils.py
aider/versioncheck.py
aider/voice.py
aider/coders/__init__.py
aider/coders/ask_coder.py
aider/coders/ask_prompts.py
aider/coders/base_coder.py
aider/coders/base_prompts.py
aider/coders/chat_chunks.py
aider/coders/editblock_coder.py
aider/coders/editblock_fenced_coder.py
aider/coders/editblock_fenced_prompts.py
aider/coders/editblock_func_coder.py
aider/coders/editblock_func_prompts.py
aider/coders/editblock_prompts.py
aider/coders/help_coder.py
aider/coders/help_prompts.py
aider/coders/search_replace.py
aider/coders/single_wholefile_func_coder.py
aider/coders/single_wholefile_func_prompts.py
aider/coders/udiff_coder.py
aider/coders/udiff_prompts.py
aider/coders/wholefile_coder.py
aider/coders/wholefile_func_coder.py
aider/coders/wholefile_func_prompts.py
aider/coders/wholefile_prompts.py
aider/queries/tree-sitter-c-tags.scm
aider/queries/tree-sitter-c_sharp-tags.scm
aider/queries/tree-sitter-cpp-tags.scm
aider/queries/tree-sitter-elisp-tags.scm
aider/queries/tree-sitter-elixir-tags.scm
aider/queries/tree-sitter-elm-tags.scm
aider/queries/tree-sitter-go-tags.scm
aider/queries/tree-sitter-java-tags.scm
aider/queries/tree-sitter-javascript-tags.scm
aider/queries/tree-sitter-ocaml-tags.scm
aider/queries/tree-sitter-php-tags.scm
aider/queries/tree-sitter-python-tags.scm
aider/queries/tree-sitter-ql-tags.scm
aider/queries/tree-sitter-ruby-tags.scm
aider/queries/tree-sitter-rust-tags.scm
aider/queries/tree-sitter-typescript-tags.scm
aider/website/index.md
aider/website/_includes/blame.md
aider/website/_includes/env-keys-tip.md
aider/website/_includes/get-started.md
robot_chat-0.51.3.dev0.dist-info/LICENSE.txt
robot_chat-0.51.3.dev0.dist-info/METADATA
robot_chat-0.51.3.dev0.dist-info/WHEEL
robot_chat-0.51.3.dev0.dist-info/entry_points.txt
robot_chat-0.51.3.dev0.dist-info/top_level.txt
robot_chat-0.51.3.dev0.dist-info/RECORD
